MANIFEST.in
README.md
setup.cfg
setup.py
braviarc/__init__.py
braviarc/braviarc.py
braviarc_homeassistant_dev.egg-info/PKG-INFO
braviarc_homeassistant_dev.egg-info/SOURCES.txt
braviarc_homeassistant_dev.egg-info/dependency_links.txt
braviarc_homeassistant_dev.egg-info/top_level.txt