Metadata-Version: 2.1
Name: braviarc-homeassistant-dev
Version: 0.3.8
Summary: bravia tv controller for home-assistant
Home-page: https://github.com/dcnielsen90/braviarc.git
Maintainer: David Nielsen
Maintainer-email: dncielsen90@gmail.com
License: UNKNOWN
Platform: UNKNOWN
Classifier: Programming Language :: Python :: 3
Classifier: License :: OSI Approved :: MIT License
Classifier: Operating System :: OS Independent
Requires-Python: >=3.6
